nonebot_plugin_sd_webui/__init__.py
nonebot_plugin_sd_webui/config.py
nonebot_plugin_sd_webui-0.1.2.dist-info/LICENSE
nonebot_plugin_sd_webui-0.1.2.dist-info/METADATA
nonebot_plugin_sd_webui-0.1.2.dist-info/WHEEL
nonebot_plugin_sd_webui-0.1.2.dist-info/RECORD
