Metadata-Version: 2.1
Name: nonebot-plugin-sd-webui
Version: 0.1.2
Summary: 
License: MIT
Author: evan-gyy
Author-email: evangu1104@foxmail.com
Requires-Python: >=3.8,<4.0
Classifier: License :: OSI Approved :: MIT License
Classifier: Programming Language :: Python :: 3
Classifier: Programming Language :: Python :: 3.8
Classifier: Programming Language :: Python :: 3.9
Classifier: Programming Language :: Python :: 3.10
Classifier: Programming Language :: Python :: 3.11
Requires-Dist: httpx
Requires-Dist: nonebot-adapter-onebot (>=2.0.0-beta.1,<3.0.0)
Requires-Dist: nonebot-plugin-guild-patch
Requires-Dist: nonebot2 (>=2.0.0-beta.1,<3.0.0)
Requires-Dist: pydantic
Requires-Dist: requests
Requires-Dist: webuiapi
